COPYING
COPYING.LESSER
MANIFEST.in
README.rst
setup.cfg
setup.py
test/__init__.py
test/base.py
test/test_assembling.py
test/test_decorators.py
test/test_dispatching.py
test/test_integration.py
test/test_interaction.py
test/test_regressions.py
test/test_utils.py
yaargh/__init__.py
yaargh/assembling.py
yaargh/compat.py
yaargh/completion.py
yaargh/constants.py
yaargh/decorators.py
yaargh/dispatching.py
yaargh/exceptions.py
yaargh/helpers.py
yaargh/interaction.py
yaargh/io.py
yaargh/utils.py
yaargh.egg-info/PKG-INFO
yaargh.egg-info/SOURCES.txt
yaargh.egg-info/dependency_links.txt
yaargh.egg-info/requires.txt
yaargh.egg-info/top_level.txt