Metadata-Version: 2.1
Name: yaargh
Version: 0.27.1
Summary: An unobtrusive argparse wrapper with natural syntax
Home-page: http://github.com/ekimekim/yaargh/
Author: Andrey Mikhaylenko
Author-email: neithere@gmail.com
Maintainer: Mike Lang
Maintainer-email: mikelang3000+yaargh@gmail.com
License: GNU Lesser General Public License (LGPL), Version 3
Keywords: cli command line argparse optparse argument option
Platform: UNKNOWN
Classifier: Development Status :: 4 - Beta
Classifier: Environment :: Console
Classifier: Intended Audience :: Developers
Classifier: Intended Audience :: Information Technology
Classifier: License :: OSI Approved :: GNU Library or Lesser General Public License (LGPL)
Classifier: Programming Language :: Python
Classifier: Programming Language :: Python :: 2
Classifier: Programming Language :: Python :: 2.7
Classifier: Programming Language :: Python :: 3
Classifier: Programming Language :: Python :: 3.4
Classifier: Programming Language :: Python :: 3.5
Classifier: Programming Language :: Python :: Implementation :: CPython
Classifier: Programming Language :: Python :: Implementation :: PyPy
Classifier: Topic :: Software Development :: User Interfaces
Classifier: Topic :: Software Development :: Libraries :: Python Modules
Provides: yaargh
Provides-Extra: import-argh
